pyce/__init__.py
pyce/_crypto.py
pyce/_imports.py
pyce/hello.py
pyce-2.0.0.dist-info/METADATA
pyce-2.0.0.dist-info/RECORD
pyce-2.0.0.dist-info/WHEEL
pyce-2.0.0.dist-info/top_level.txt
