Metadata-Version: 2.1
Name: pyce
Version: 2.0.0
Summary: Execute encrypted Python bytecode.
Home-page: https://github.com/soroco/pyce
Author: Soroco Americas Private Limited
Author-email: opensource@soroco.com
Maintainer: Soroco Americas Private Limited
Maintainer-email: opensource@soroco.com
License: Apache Software License Version 2.0
Keywords: cryptography encryption import pyce
Platform: Windows 10
Platform: Windows Server 2008
Platform: Windows Server 2012
Platform: Linux
Classifier: Development Status :: 5 - Production/Stable
Classifier: Intended Audience :: Developers
Classifier: Topic :: Security :: Cryptography
Classifier: Topic :: Software Development :: Build Tools
Classifier: License :: OSI Approved :: Apache Software License
Classifier: Operating System :: Microsoft :: Windows :: Windows 10
Classifier: Operating System :: Microsoft :: Windows :: Windows Server 2008
Classifier: Operating System :: POSIX :: Linux
Classifier: Programming Language :: Python :: 3.7
Requires-Python: >=3.7, <3.8
Requires-Dist: cryptography (==2.3.1)
